{"#1":"JWNaldo","#2":"Copperkid","#3":"PachoBlues","#4":"xJoaoVictor2006","#5":"lpmello84","#6":"Danacrisc","#7":"DaniloCalvalhan","#8":"AbnerOriel","#9":"GabrielYehovah","#10":"wmoliva","#11":"Rargef","#12":"Hgp2306","#13":"Yuri220","#14":"ShainnerSenpai","#15":"Andre10Salles","#16":"Zarddy","#17":"DanielP4l4d1n0","#18":"LihPelinson","#19":"JVitorAmaral","#20":"Caio06342","#21":"nathassiaaa","#22":"TrnrLucas10","#23":"SSchneider33","#24":"6rajraj9","#25":"Quindinzinho97","#26":"PachirisuDaDawn","#27":"AureoCerezer","#28":"JamMustang","#29":"IchiroFukuda","#30":"hutral","#31":"ThiagoEloyy","#32":"XxRFPOxX","#33":"BruceSantos","#34":"Danilo8708","#35":"Barbosafc","#36":"FiEmery","#37":"PaulinhoTad","#38":"RickManzato","#39":"Maaelangelii","#40":"BTowersKA","#41":"NaraLago","#42":"Brunaaaauum","#43":"marcuspopo","#44":"GianRedghost","#45":"BeFricke","#46":"CalmaMoreno","#47":"ViniConrado97","#48":"V1v12n","#49":"fernanomaster","#50":"FrankWill","#51":"PrazerChris","#52":"Gabzis","#53":"beergaaa","#54":"JungonJungon","#55":"Umbuw","#56":"Kino26LL","#57":"Wenigengel","#58":"GustavoYoukai","#59":"MillerLav","#60":"Leaozinho","#61":"LeunammeGO","#62":"llRenanJafall","#63":"MaximeCraft","#64":"Washingtonpk1","#65":"Anteriin","#66":"Postin","#67":"K1ngNier","#68":"Anderlanm","#69":"Pedro367428","#70":"Hybridonn","#71":"Nightmare9113","#72":"Nilimpetuoso","#73":"franciscofrr","#74":"Edersongomes01","#75":"Rafa1cs","#76":"RaltsDoWally","#77":"sachura77","#78":"wpachecao","#79":"IgorIate","#80":"srateta","#81":"VictorHug09","#82":"PatrickSRN","#83":"Faduzim","#84":"Allishow10","#85":"soul9litch","#86":"RubenCanudo","#87":"Grandjyn","#88":"Augusto11082006","#89":"brunohadji","#90":"Dinagoras","#91":"LincaoXD","#92":"Silvarts","#93":"Lokoferas","#94":"danielrg98","#95":"Firmin0wtwo30","#96":"Leticiaa29","#97":"MavrousIZN","#98":"Jojomura","#99":"jeff05valor","#100":"rennangardoni","#101":"BobMendesBR","#102":"EhhhUsGuri","#103":"LawrenceLtyear","#104":"johnbrumano","#105":"thiasccp","#106":"Zellgades","#107":"Amancio1401","#108":"l4pdenis","#109":"Paulonetaaa09","#110":"JeanCostaJesus","#111":"MestreMendes25","#112":"FFernan10","#113":"bibivenditti","#114":"carlosPianta","#115":"Mustang2795","#116":"Hamuzeira","#117":"FranKDA7","#118":"LTiugansii","#119":"JosihelCBF","#120":"Felipemelokkk","#121":"Bruninho69","#122":"Ian93juca","#123":"OrochiDsM","#124":"ImperadordoMarX","#125":"Kourlash","#126":"PitBandicoot","#127":"MaelAngeli","#128":"LeeoBadboy","#129":"Anders0nc0sta","#130":"mferratto","#131":"giantboulder","#132":"XGUIKEN","#133":"Alves75","#134":"LucLos","#135":"J34N147","#136":"Barros","#137":"GusNovalis","#138":"TheVPSF","#139":"01SgtBrave","#140":"EsdrasLBA","#141":"HyPiN0S","#142":"Toxicosdiversos","#143":"rxLinkCarvalho","#144":"MariaCabralz","#145":"Jhonnedenis44","#146":"DanAvec","#147":"ReiiiThur","#148":"RNeto1999","#149":"Lwingzz","#150":"MAJ3STIC99","#151":"GLL182","#152":"ProfessorWilmer","#153":"Marciano0017","#154":"Yoshiedson","#155":"DarknessKyu","#156":"NakaMH19","#157":"TomLibanio","#158":"MasterOfReality","#159":"Mainha03","#160":"loipinheiro","#161":"Felipeborges28","#162":"TaisFigueroa","#163":"GuiliMash","#164":"robertsouzam","#165":"erikacostalima","#166":"RafaXu22","#167":"Ismahell","#168":"Mateusvalerio","#169":"Wallacesd","#170":"FelipeCaRamalho","#171":"GabAndrey","#172":"RphRodrigues","#173":"Ledzep07","#174":"Killjoypg","#175":"YuriUsedFly","#176":"Liberalino","#177":"Logan94","#178":"Sirlenekiba","#179":"LordV610r","#180":"HullkR","#181":"Hugo00m","#182":"Matheusbigdaddy","#183":"Dinodinossaura","#184":"lukamrs","#185":"CiAnNeto","#186":"Hatiim","#187":"racsphd","#188":"Felipesp3456","#189":"JoaoNeves200","#190":"Abmdragond","#191":"Kaiorf","#192":"LetsGoGyarados","#193":"NathanJettar1","#194":"PedroAC07","#195":"Kobinha23","#196":"ThenWhyNot","#197":"MetallicaJunior","#198":"ShoutOutToBR","#199":"Xexeu007","#200":"007RefriAsh","#201":"Sonozzy","#202":"Thiagolima04","#203":"Bittenca","#204":"GeneralLeonardo","#205":"WallBrPower","#206":"MrXanddy","#207":"Fernandim88","#208":"PicasoRC","#209":"EvertonCMachado","#210":"LOPES1512","#211":"ErickRagnarson","#212":"TinhoStyle","#213":"JoaoLeXavier","#214":"RecrutaER","#215":"dehdis","#216":"KahB57_yt","#217":"Caiozuzuz","#218":"Willraphas","#219":"LuisRJ21","#220":"AWildPinguim","#221":"IrvingVegano","#222":"Zambleman","#223":"Myla582","#224":"SirLucasAkio","#225":"RuudG007","#226":"renamolo22364","#227":"CleristonVieira","#228":"xXJohnVitorXx","#229":"Gankakudias","#230":"kdminhaconta","#231":"Batto001","#232":"TheGaviao","#233":"Aquor002","#234":"LeoBgi018","#235":"PatrickyAlbani","#236":"jvcpBR","#237":"Alves76522","#238":"GustavoGamer457","#239":"DerekFernanfo","#240":"Ryuuzaki1316","#241":"xxEdddxx","#242":"EDIPAOQSHINY","#243":"ZyroBerkXL","#244":"Marcosvsm82","#245":"LeoRezende88","#246":"JoeWillian","#247":"Lucascaico12","#248":"Hudyps93","#249":"Rlrothemann","#250":"Lausenger","#251":"ThallesFSantos","#252":"Mahack6","#253":"MattCust","#254":"Coutinho805","#255":"ReftSquad","#256":"JoaquimBrondani","#257":"Beninho2015","#258":"ChuckSR","#259":"BrunoPeron82","#260":"MestreDoSquad","#261":"Macciola","#262":"NasciMonsters","#263":"AlphaLeonN","#264":"ECPelike","#265":"AlCunha33","#266":"42Marcelo","#267":"Wellsheldon","#268":"ViniBorgess10","#269":"CAIERAGOD","#270":"Bragabis","#271":"Raphaaaaaael","#272":"01PHP","#273":"DouglasAzeredo","#274":"LufeMatiusso","#275":"CledilsonRock93","#276":"yDuDuLe1","#277":"Wallycastro","#278":"KlausMyth","#279":"Gustavovso","#280":"bbast0s","#281":"Bruno2nunes","#282":"fredbianchi","#283":"MoisesPknGo","#284":"Gbbernardoo","#285":"MariaAntoniaRJ","#286":"GuiDSGomes","#287":"Seilah77EGE","#288":"AndreyAvilla","#289":"Dkcerberus","#290":"aaaaaaaaaaQPOHA","#291":"FCReboucas","#292":"FofaoRadical","#293":"seraosleumas","#294":"burntbread11","#295":"Welce10","#296":"TheGugaa","#297":"ZzAndromedazZ","#298":"JayaOkada","#299":"Corinthians10","#300":"ValarM0rghuls","#301":"1RhuanFelippe1","#302":"DiSenesi","#303":"Renato0Ze","#304":"andersonbobby","#305":"JhonOliveira10","#306":"Ricellylb","#307":"ProfNobrega","#308":"Guleal147","#309":"withebaityou","#310":"DANMOS7","#311":"Andrellus","#312":"R3N3R4715D","#313":"Joaaoopoket","#314":"DihNalin","#315":"LMJBRAZIL1","#316":"ANDERSONSFBR","#317":"SUNtrosko","#318":"PizzaDelivery","#319":"FRANKLINROCK","#320":"KrisAlucard","#321":"GabrielCastr007","#322":"ZeDoSambaxxx","#323":"hinata1527","#324":"TaikiriSaruman","#325":"lilomunhos","#326":"AnderBaracho","#327":"Didi1977","#328":"Yasulista","#329":"TheBestGarcia","#330":"RenatoAc31","#331":"Coroachato","#332":"caioLim4","#333":"HaardFV","#334":"Jecatherina","#335":"Paulovgv007","#336":"Tautenhain1","#337":"MarcioXYZ","#338":"Limaabner25","#339":"XYSllagrymaYX","#340":"ArielRuther","#341":"Argila","#342":"voiDzz1","#343":"S0LUC0","#344":"DudumonXY","#345":"Lagranha","#346":"TeoS556","#347":"gostzin","#348":"Italook","#349":"LimaArleson","#350":"JuniorFaarias","#351":"LliwLopes","#352":"XavecoJoao","#353":"JohnSimoes99","#354":"montonevlogs","#355":"mileregou","#356":"Theonescanor","#357":"Extreme78","#358":"Lipevolpi12","#359":"EvansRitzel","#360":"Murdock3215","#361":"RafaCarolPrado","#362":"Evaldofilhoo","#363":"brunofo18","#364":"JuniorRubempre","#365":"andorekenchan","#366":"caiioLim4","#367":"Lrmarcaljr","#368":"ScientistMike08","#369":"LoboKetchum81","#370":"Beiruteyes","#371":"016Kelvin","#372":"Soulindo95","#373":"MDeAzevedo","#374":"fantasminha","#375":"BreakBruno","#376":"FTSTCNoName","#377":"Lucasneee","#378":"CarlosWessling","#379":"GabsL08","#380":"LucasEduardo91","#381":"BaraoPK","#382":"DushtanoJoey","#383":"Lipe bolzan","#384":"PocoYo16","#385":"baresta","#386":"Lukinhasdz77","#387":"giftflyZ","#388":"Gerson","#389":"LuannPhillips","#390":"Rapha26R","#391":"MarcosCaseira","#392":"Rique627","#393":"GederEller","#394":"Uapuem","#395":"cortarts","#396":"JaoPretoo","#397":"OlegaOliveira","#398":"115rj","#399":"Phvintetres","#400":"ATomy","#401":"RNReis","#402":"Jjestone","#403":"Eveferr1","#404":"FSCASTANON","#405":"MiraiToranksu","#406":"FelipeB0rgess","#407":"TeobaldoE","#408":"LokoDosArames","#409":"xxVOLKNERxx","#410":"DanielAugusto","#411":"JonhPendragon","#412":"Emiliana75","#413":"fantasminha688","#414":"Ryan1229super","#415":"Henriqjm1990","#416":"Acostenha","#417":"GisaDylon","#418":"Maguugam","#419":"CacahLacerda","#420":"Ffaabricioo","#421":"Perukadgs","#422":"Pedro455-","#423":"Minixexeu","#424":"LuuizMaatheus","#425":"alex23111986","#426":"ejuliocrl7","#427":"BrancoFonseca","#428":"PlusTopTean","#429":"GabrielNolte","#430":"Legend2BR","#431":"Anaaluiz4","#432":"xPL4Y3R1x","#433":"Bl4cklivematter","#434":"MrSchaeffer","#435":"88Nossila","#436":"XxDartaNxX","#437":"WellKING1","#438":"TamagXolitario","#439":"VantuildesTUTU","#440":"Edgarmat1","#441":"KomachiHero","#442":"jbarbosa","#443":"marcelofasal","#444":"Samuraykarate","#445":"rogerblake","#446":"GscRed","#447":"Ghunnter","#448":"Cassiogrimmler","#449":"Brun0Guerra","#450":"DominusRay25","#451":"LordKagruel","#452":"deivisaldren","#453":"LucasBonanzi","#454":"Mumassauro","#455":"luanvitozxc","#456":"JRRS96","#457":"Pedreams","#458":"Yuricaldas95","#459":"Henrisathler","#460":"Jhunio86","#461":"AmadeuFL","#462":"BrunoHunterr","#463":"Marxtomm","#464":"DracoNery","#465":"Bobfilho","#466":"Bernardjoe","#467":"soaresof","#468":"BryanGalo10","#469":"RafaelSSEnzo","#470":"SarinaSchneider","#471":"Andresiqueira04","#472":"carloscarvalhoj","#473":"MasterGuhhh1","#474":"ReiMysticJorel","#475":"PamhFerreira","#476":"AlleMuller","#477":"MadMaxxMaximus","#478":"PokeAXFennix","#479":"PedroAvCon17","#480":"DonovanCarvalho","#481":"JthaSanches","#482":"Abextadoooo","#483":"EuDaniloGabriel","#484":"Aledara3383","#485":"MrNelsao","#486":"Binhozika01","#487":"Zenakinhow","#488":"Olyneon","#489":"Slashabreu","#490":"FeanorEss","#491":"Israelberbigier","#492":"Filipemelo17","#493":"Mariomfj","#494":"jorgebfilho","#495":"Maumausq","#496":"Fir3mind","#497":"Priiscilas2","#498":"Onjatep","#499":"DegoTheHammer","#500":"Reevoltz00","#501":"Jvalcn","#502":"1pierre0073","#503":"Richard4KS","#504":"TrainerSteinar","#505":"JayPhellll","#506":"Collares245","#507":"Tigman1986","#508":"MassaoGuskuma","#509":"013Mabilabrisa","#510":"OmeleteDeTogepi","#511":"Sofiadamae","#512":"Aaaak3"}