{"#1":"R0ssinh0","#2":"JWNaldo","#3":"Zarddy","#4":"XxRFPOxX","#5":"Hgp2306","#6":"LihPelinson","#7":"Danilo8708","#8":"Andre10Salles","#9":"JVitorAmaral","#10":"Bruninho69","#11":"PaulinhoTad","#12":"Danacrisc","#13":"SSchneider33","#14":"PrazerChris","#15":"PachirisuDaDawn","#16":"MestreMendes25","#17":"IchiroFukuda","#18":"Dricolino21","#19":"Yuri220","#20":"AureoCerezer","#21":"BruceSantos","#22":"6rajraj9","#23":"Postin","#24":"Augusto11082006","#25":"Wenigengel","#26":"J34N147","#27":"DaniloCalvalhan","#28":"MillerLav","#29":"soul9litch","#30":"Firmin0wtwo30","#31":"VictorHug09","#32":"Hybridonn","#33":"RickManzato","#34":"Copperkid","#35":"giantboulder","#36":"JamMustang","#37":"JeanCostaJesus","#38":"Caio06342","#39":"V1v12n","#40":"Pedro367428","#41":"danielrg98","#42":"Rargef","#43":"Ismahell","#44":"Umbuw","#45":"GabrielYehovah","#46":"PachoBlues","#47":"PedroAC07","#48":"fernanomaster","#49":"Gabzis","#50":"Kino26LL","#51":"Maaelangelii","#52":"AbnerOriel","#53":"OrochiDsM","#54":"sachura77","#55":"Hatiim","#56":"JungonJungon","#57":"MaximeCraft","#58":"NathanJettar1","#59":"DanielP4l4d1n0","#60":"Fernandim88","#61":"Mainha03","#62":"wmoliva","#63":"Washingtonpk1","#64":"Zellgades","#65":"BTowersKA","#66":"MrXanddy","#67":"ErickRagnarson","#68":"CalmaMoreno","#69":"Mustang2795","#70":"Nilimpetuoso","#71":"Leaozinho","#72":"RubenCanudo","#73":"ReiiiThur","#74":"rennangardoni","#75":"KahB57_yt","#76":"FrankWill","#77":"PatrickSRN","#78":"MavrousIZN","#79":"Lwingzz","#80":"renamolo22364","#81":"DarknessKyu","#82":"RuudG007","#83":"YuriBrCe","#84":"FranKDA7","#85":"PatrickyAlbani","#86":"RafaCarolPrado","#87":"ThiagoEloyy","#88":"lpmello84","#89":"Toxicosdiversos","#90":"Matheusbigdaddy","#91":"Marcosvsm82","#92":"ZzAndromedazZ","#93":"MaelAngeli","#94":"NaraLago","#95":"Mahack6","#96":"DerekFernanfo","#97":"Killjoypg","#98":"TrnrLucas10","#99":"thiasccp","#100":"wpachecao","#101":"Coutinho805","#102":"Wallacesd","#103":"ShainnerSenpai","#104":"Quindinzinho97","#105":"lukamrs","#106":"Nightmare9113","#107":"Silvarts","#108":"Liberalino","#109":"nathassiaaa","#110":"CAIERAGOD","#111":"LOPES1512","#112":"MariaCabralz","#113":"TheVPSF","#114":"hutral","#115":"Dinagoras","#116":"marcuspopo","#117":"Beninho2015","#118":"Hugo00m","#119":"XJoaoVgmr2006X","#120":"Alves75","#121":"LincaoXD","#122":"caiioLim4","#123":"AndreyAvilla","#124":"GeneralLeonardo","#125":"Xexeu007","#126":"MasterOfReality","#127":"MariaAntoniaRJ","#128":"Mateusvalerio","#129":"PizzaDelivery","#130":"FelipedeCastroR","#131":"HyPiN0S","#132":"GustavoYoukai","#133":"EsdrasLBA","#134":"IgorIate","#135":"EhhhUsGuri","#136":"Corinthians10","#137":"ValarM0rghuls","#138":"Batto001","#139":"Yoshiedson","#140":"Anderlanm","#141":"Lliw","#142":"Guleal147","#143":"Amancio1401","#144":"withebaityou","#145":"DANMOS7","#146":"LeunammeGO","#147":"EDIPAOQSHINY","#148":"ANDERSONSFBR","#149":"Anteriin","#150":"BobMendesBR","#151":"FiEmery","#152":"KrisAlucard","#153":"HullkR","#154":"01SgtBrave","#155":"llRenanJafall","#156":"lilomunhos","#157":"franciscofrr","#158":"OmeleteDeTogepi","#159":"caioLim4","#160":"ViniConrado97","#161":"LeeoBadboy","#162":"Paulonetaaa09","#163":"AnderBaracho","#164":"Barbosafc","#165":"HaardFV","#166":"carlosPianta","#167":"Myla582","#168":"racsphd","#169":"Jojomura","#170":"S0LUC0","#171":"GusNovalis","#172":"gostzin","#173":"MrNelsao","#174":"Anders0nc0sta","#175":"mileregou","#176":"JohnSimoes99","#177":"Seilah77EGE","#178":"MDeAzevedo","#179":"Extreme78","#180":"Allishow10","#181":"EvansRitzel","#182":"Murdock3215","#183":"ArielRuther","#184":"JuniorRubempre","#185":"xXJohnVitorXx","#186":"AWildPinguim","#187":"xLudvig","#188":"Ian93juca","#189":"Ledzep07","#190":"LoboKetchum81","#191":"LuisRJ21","#192":"Jhunio86","#193":"fantasminha","#194":"Zenakinhow","#195":"CarlosWessling","#196":"Lucasneee","#197":"MasterGuhhh1","#198":"Lagranha","#199":"DracoNery","#200":"Anaaluiz4","#201":"DushtanoJoey","#202":"PocoYo16","#203":"Gerson","#204":"CiAnNeto","#205":"Rapha26R","#206":"Caiozuzuz","#207":"Rique627","#208":"JayaOkada","#209":"JaoPretoo","#210":"xxEdddxx","#211":"GuiDSGomes","#212":"seraosleumas","#213":"Phvintetres","#214":"Kaiorf","#215":"leh29","#216":"BeFricke","#217":"beergaaa","#218":"Raphaaaaaael","#219":"ATomy","#220":"giftflyZ","#221":"RphRodrigues","#222":"FSCASTANON","#223":"Alex90oliveira","#224":"CleristonVieira","#225":"LoxSP","#226":"CledilsonRock93","#227":"Zambleman","#228":"FFernan10","#229":"01PHP","#230":"Macciola","#231":"Sofiadamae","#232":"GuiliMash","#233":"ImperadordoMarX","#234":"alex23111986","#235":"TeobaldoE","#236":"Wellsheldon","#237":"Henrisathler","#238":"Gbbernardoo","#239":"Soulindo95","#240":"XxDartaNxX","#241":"marcelofasal","#242":"ReiMysticJorel","#243":"Lausenger","#244":"DominusRay25","#245":"Acostenha","#246":"GscRed","#247":"DanielGaldi","#248":"JoeWillian","#249":"Didi1977","#250":"AlCunha33","#251":"deivisaldren","#252":"rxLinkCarvalho","#253":"Bruno2nunes","#254":"LucasBonanzi","#255":"xxVOLKNERxx","#256":"Coroachato","#257":"Yuricaldas95","#258":"Argila","#259":"AmadeuFL","#260":"BrunoHunterr","#261":"Lipevolpi12","#262":"Marxtomm","#263":"Lrmarcaljr","#264":"NakaMH19","#265":"Bernardjoe","#266":"Bortuluzi","#267":"soaresof","#268":"SarinaSchneider","#269":"FofaoRadical","#270":"MadMaxxMaximus","#271":"Legend2BR","#272":"PicasoRC","#273":"TinhoStyle","#274":"ejuliocrl7","#275":"Abextadoooo","#276":"LordV610r","#277":"Andresiqueira04","#278":"jeff05valor","#279":"Willraphas","#280":"Slashabreu","#281":"TheGaviao","#282":"42Marcelo","#283":"Israelberbigier","#284":"Dkcerberus","#285":"GabrielCastr007","#286":"BrunoPeron82","#287":"Mariomfj","#288":"Olyneon","#289":"bbast0s","#290":"Rafa1cs","#291":"Brunaaaauum","#292":"bibivenditti","#293":"Mumassauro","#294":"MassaoGuskuma","#295":"013Mabilabrisa","#296":"Jhonnedenis44","#297":"GabsL08","#298":"K1ngNier","#299":"GustavoFdeSouza","#300":"LucasVdCarvalho","#301":"TeoS556","#302":"Priiscilas2","#303":"CarlosCostta","#304":"MiraiToranksu","#305":"SirLucasAkio","#306":"Anderson2374"}