{"#1":"Copperkid","#2":"PachoBlues","#3":"xJoaoVictor2006","#4":"Hgp2306","#5":"JWNaldo","#6":"wmoliva","#7":"lpmello84","#8":"PachirisuDaDawn","#9":"Yuri220","#10":"AureoCerezer","#11":"Andre10Salles","#12":"DaniloCalvalhan","#13":"AbnerOriel","#14":"Zarddy","#15":"Danacrisc","#16":"LNDsRargef","#17":"TrnrLucas10","#18":"BruceSantos","#19":"DanielP4l4d1n0","#20":"Caio06342","#21":"LihPelinson","#22":"6rajraj9","#23":"RickManzato","#24":"SSchneider33","#25":"hutral","#26":"nathassiaaa","#27":"Quindinzinho97","#28":"ShainnerSenpai","#29":"IchiroFukuda","#30":"beergaaa","#31":"Danilo8708","#32":"GabrielYehovah","#33":"brunohadji","#34":"JamMustang","#35":"JVitorAmaral","#36":"Barbosafc","#37":"BeFricke","#38":"Allishow10","#39":"Wenigengel","#40":"llRenanJafall","#41":"Anderlanm","#42":"fernanomaster","#43":"FrankWill","#44":"ThiagoEloyy","#45":"Maaelangelii","#46":"Ian93juca","#47":"VictorHug09","#48":"FiEmery","#49":"NaraLago","#50":"Umbuw","#51":"GianRedghost","#52":"XxRFPOxX","#53":"Brunaaaauum","#54":"BobMendesBR","#55":"Kino26LL","#56":"ViniConrado97","#57":"V1v12n","#58":"Gabzis","#59":"RaltsDoWally","#60":"Edersongomes01","#61":"PaulinhoTad","#62":"ShoutOutToBR","#63":"K1ngNier","#64":"johnbrumano","#65":"marcuspopo","#66":"Leaozinho","#67":"MaximeCraft","#68":"PrazerChris","#69":"BTowersKA","#70":"Firmin0wtwo30","#71":"Silvarts","#72":"murilosou","#73":"Amancio1401","#74":"CalmaMoreno","#75":"IgorIate","#76":"MasterOfReality","#77":"Rikudou45","#78":"JungonJungon","#79":"RphRodrigues","#80":"Anteriin","#81":"GustavoYoukai","#82":"l4pdenis","#83":"srateta","#84":"Felipemelokkk","#85":"wpachecao","#86":"MillerLav","#87":"carlosPianta","#88":"LeunammeGO","#89":"PitBandicoot","#90":"Sonozzy","#91":"Washingtonpk1","#92":"FelipeCaRamalho","#93":"Postin","#94":"Kaiorf","#95":"Anders0nc0sta","#96":"Pedro367428","#97":"Hybridonn","#98":"JosihelCBF","#99":"Nilimpetuoso","#100":"franciscofrr","#101":"PatrickSRN","#102":"MestreMendes25","#103":"J34N147","#104":"EvertonCMachado","#105":"XGUIKEN","#106":"LincaoXD","#107":"LufeMatiusso","#108":"Rafa1cs","#109":"007RefriAsh","#110":"EhhhUsGuri","#111":"Faduzim","#112":"Nightmare9113","#113":"Paulonetaaa09","#114":"TaisFigueroa","#115":"Grandjyn","#116":"RubenCanudo","#117":"Lokoferas","#118":"soul9litch","#119":"Mateusvalerio","#120":"Augusto11082006","#121":"Logan94","#122":"Dinagoras","#123":"Dkcerberus","#124":"sachura77","#125":"GeneralLeonardo","#126":"Alves75","#127":"danielrg98","#128":"Bittenca","#129":"robertsouzam","#130":"HullkR","#131":"TheVPSF","#132":"MavrousIZN","#133":"Jojomura","#134":"EsdrasLBA","#135":"jeff05valor","#136":"RNeto1999","#137":"rennangardoni","#138":"thiasccp","#139":"Caiozuzuz","#140":"giantboulder","#141":"Zellgades","#142":"LeoBgi018","#143":"Leticiaa29","#144":"FFernan10","#145":"bibivenditti","#146":"JeanCostaJesus","#147":"Killjoypg","#148":"ImperadordoMarX","#149":"Mustang2795","#150":"Barros2094","#151":"Alves76522","#152":"Hamuzeira","#153":"Polemarkhos","#154":"HyPiN0S","#155":"LawrenceLtyear","#156":"yDuDuLe1","#157":"FranKDA7","#158":"Wallacesd","#159":"LTiugansii","#160":"01PHP","#161":"R3zinnnn","#162":"seraosleumas","#163":"Toxicosdiversos","#164":"angelormsf","#165":"Fernandim88","#166":"MbigD4ddy","#167":"Bruninho69","#168":"GustavoGamer457","#169":"OrochiDsM","#170":"Kourlash","#171":"Lausenger","#172":"Jhonnedenis44","#173":"AnderBaracho","#174":"MaelAngeli","#175":"MasterGuhhh1","#176":"mferratto","#177":"016Kelvin","#178":"BrunoPeron82","#179":"fredbianchi","#180":"AlCunha33","#181":"LeoRezende88","#182":"ClaudioCalarezi","#183":"DudumonXY","#184":"MarechalGuga157","#185":"ChuckSR","#186":"GuiliMash","#187":"DouglasAzeredo","#188":"Gbbernardoo","#189":"01SgtBrave","#190":"rxLinkCarvalho","#191":"burntbread11","#192":"JoeWillian","#193":"DanielGaldi","#194":"DanAvec","#195":"ReiiiThur","#196":"LeeoBadboy","#197":"LNDsWingzz","#198":"MAJ3STIC99","#199":"JoaquimBrondani","#200":"GLL182","#201":"ProfessorWilmer","#202":"Marciano0017","#203":"Yoshiedson","#204":"MariaCabralz","#205":"DarknessKyu","#206":"Myla582","#207":"NakaMH19","#208":"Mainha03","#209":"loipinheiro","#210":"xRNM7","#211":"Felipeborges28","#212":"MattCust","#213":"LNDsIsmahell","#214":"MDeAzevedo","#215":"Beninho2015","#216":"LordV610r","#217":"LetsGoGyarados","#218":"kdminhaconta","#219":"GabAndrey","#220":"LucLos","#221":"Joaaoopoket","#222":"DTheHammer","#223":"Ledzep07","#224":"GusNovalis","#225":"Thiagolima04","#226":"YuriUsedFly","#227":"PedroAC07","#228":"NasciMonsters","#229":"Liberalino","#230":"42Marcelo","#231":"Sirlenekiba","#232":"erikacostalima","#233":"Hugo00m","#234":"Dinodinossaura","#235":"Aquor002","#236":"ZyroBerkXL","#237":"lukamrs","#238":"Argila","#239":"iNinjaGay","#240":"KlausMyth","#241":"Eveferr1","#242":"Hatiim","#243":"Didi1977","#244":"racsphd","#245":"ArielRuther","#246":"JoaoNeves200","#247":"Felipesp3456","#248":"Henriqjm1990","#249":"Abmdragond","#250":"LNDsNthanJettar","#251":"Perukadgs","#252":"CledilsonRock93","#253":"RecrutaER","#254":"Kobinha23","#255":"ThenWhyNot","#256":"MetallicaJunior","#257":"DiSenesi","#258":"JhonOliveira10","#259":"RafaXu22","#260":"JohnSimoes99","#261":"TeslanAtlas","#262":"AdegaPrincipado","#263":"Kakasus","#264":"Lucascaico12","#265":"EDIPAOQSHINY","#266":"MrXanddy","#267":"deivisaldren","#268":"LOPES1512","#269":"ErickRagnarson","#270":"Bragabis","#271":"TinhoStyle","#272":"JoaoLeXavier","#273":"Tautenhain1","#274":"Coutinho805","#275":"BrZsLeonel","#276":"magatrevosa","#277":"dehdis","#278":"Brun0Guerra","#279":"GuiDSGomes","#280":"MasterHB100","#281":"KahB57_yt","#282":"Mahack6","#283":"Willraphas","#284":"FcLNDsBernardo","#285":"Luck11973","#286":"TheGaviao","#287":"LuisRJ21","#288":"JOROMANETOPI","#289":"AWildPinguim","#290":"IrvingVegano","#291":"FelipeB0rgess","#292":"Zambleman","#293":"CiAnNeto","#294":"SirLucasAkio","#295":"RuudG007","#296":"renamolo22364","#297":"CleristonVieira","#298":"Gankakudias","#299":"Batto001","#300":"Anaaluiz4","#301":"PatrickyAlbani","#302":"jvcpBR","#303":"TomLibanio","#304":"DerekFernanfo","#305":"Ryuuzaki1316","#306":"xxEdddxx","#307":"Andrellus","#308":"JayaOkada","#309":"RenatoNeves01","#310":"Marcosvsm82","#311":"Hudyps93","#312":"GustavoAsh","#313":"Xexeu007","#314":"ReftSquad","#315":"PaiDoLuke7","#316":"rogerblake","#317":"Kau198","#318":"Rlrothemann","#319":"Macciola","#320":"MestreDoSquad","#321":"ECPelike","#322":"Wellsheldon","#323":"Lrmarcaljr","#324":"ViniBorgess10","#325":"CAIERAGOD","#326":"ThallesFSantos","#327":"MagnataSlz","#328":"Raphaaaaaael","#329":"BabiSyl","#330":"Wallycastro","#331":"Amaury1551","#332":"Gustavovso","#333":"Luisgoleirogx","#334":"TaikiriSaruman","#335":"bbast0s","#336":"Bruno2nunes","#337":"MoisesPknGo","#338":"MariaAntoniaRJ","#339":"Paul_falconeer","#340":"xXJohnVitorXx","#341":"AlphaLeonN","#342":"Ooooodaiiii","#343":"Lukinhasdz77","#344":"Seilah77EGE","#345":"Andrechal","#346":"AndreyAvilla","#347":"Guleal147","#348":"aaaaaaaaaaQPOHA","#349":"Paulovgv007","#350":"FCReboucas","#351":"SUNtrosko","#352":"FofaoRadical","#353":"WallBrPower","#354":"Ffaabricioo","#355":"JonhPendragon","#356":"Welce10","#357":"RafaCarolPrado","#358":"LliwLopes","#359":"TheGugaa","#360":"ZzAndromedazZ","#361":"PicasoRC","#362":"85984022355","#363":"Jbcampelo","#364":"Corinthians10","#365":"ValarM0rghuls","#366":"1RhuanFelippe1","#367":"Minixexeu","#368":"Renato0Ze","#369":"andersonbobby","#370":"MestreKaryne","#371":"withebaityou","#372":"DANMOS7","#373":"DihNalin","#374":"GabrielNolte","#375":"ambersinoh","#376":"LMJBRAZIL1","#377":"ANDERSONSFBR","#378":"PlusTopTean","#379":"voiDzz1","#380":"Sh4dowBan","#381":"PizzaDelivery","#382":"Pronemarmote","#383":"Jhunio86","#384":"FRANKLINROCK","#385":"KrisAlucard","#386":"GabrielCastr007","#387":"Radythys","#388":"ZeDoSambaxxx","#389":"MisterEnzinho10","#390":"FabianoBB","#391":"hinata1527","#392":"jujubacristani","#393":"lilomunhos","#394":"Yasulista","#395":"Igorfdeoliv","#396":"TheBestGarcia","#397":"RenatoAc31","#398":"Coroachato","#399":"GustavoTanusF11","#400":"Lesskid","#401":"caioLim4","#402":"MichaelZoombie","#403":"HaardFV","#404":"DementePPM","#405":"Jecatherina","#406":"GioLuigi13","#407":"JanderDuran","#408":"XYSllagrymaYX","#409":"Limaabner25","#410":"Onjatep","#411":"S0LUC0","#412":"ThaysAbrew","#413":"Lagranha","#414":"TeoS556","#415":"gostzin","#416":"montonevlogs","#417":"Italook","#418":"ProfNobrega","#419":"JuniorLessa","#420":"LimaArleson","#421":"JuniorFaarias","#422":"XavecoJoao","#423":"Edgarmat1","#424":"mileregou","#425":"Theonescanor","#426":"Extreme78","#427":"Lipevolpi12","#428":"LoboKetchum81","#429":"PamhFerreira","#430":"EvansRitzel","#431":"Reevoltz00","#432":"Murdock3215","#433":"BarrelCanine","#434":"Evaldofilhoo","#435":"jmarcosm11","#436":"brunofo18","#437":"JuniorRubempre","#438":"andorekenchan","#439":"caiioLim4","#440":"ScientistMike08","#441":"Beiruteyes","#442":"YurySSLindo","#443":"MFerreirinha","#444":"Soulindo95","#445":"fantasminha","#446":"BreakBruno","#447":"FTSTCNoName","#448":"Lucasneee","#449":"KukaMPK","#450":"CarlosWessling","#451":"GabsL08","#452":"Andremrc","#453":"LucasEduardo91","#454":"BaraoPK","#455":"DushtanoJoey","#456":"Lipe bolzan","#457":"PocoYo16","#458":"baresta","#459":"giftflyZ","#460":"Gerson","#461":"LuannPhillips","#462":"Rapha26R","#463":"MarcosCaseira","#464":"Rique627","#465":"GederEller","#466":"Uapuem","#467":"cortarts","#468":"JaoPretoo","#469":"Dannyyllo","#470":"OlegaOliveira","#471":"115rj","#472":"MaguinhInSpirit","#473":"Eshoiti98","#474":"Pudim8D","#475":"Phvintetres","#476":"Marcin3sssbola","#477":"ATomy","#478":"RNReis","#479":"Jjestone","#480":"Letartaaaa","#481":"XandaoThug","#482":"FSCASTANON","#483":"MiraiToranksu","#484":"Theusss19968","#485":"TeobaldoE","#486":"LokoDosArames","#487":"RicharlysCruz","#488":"xxVOLKNERxx","#489":"DanielAugusto","#490":"Emiliana75","#491":"fantasminha688","#492":"Ryan1229super","#493":"Gustavobc0","#494":"Acostenha","#495":"GisaDylon","#496":"Maguugam","#497":"CacahLacerda","#498":"Barufii","#499":"Pedro455-","#500":"LuuizMaatheus","#501":"alex23111986","#502":"ejuliocrl7","#503":"BrancoFonseca","#504":"Legend2BR","#505":"Bl4cklivematter","#506":"MrSchaeffer","#507":"88Nossila","#508":"XxDartaNxX","#509":"WellKING1","#510":"TamagXolitario","#511":"VantuildesTUTU","#512":"KomachiHero","#513":"jbarbosa","#514":"marcelofasal","#515":"GURIINCRIVEL95","#516":"Lunaticleader09","#517":"GscRed","#518":"Ghunnter","#519":"Greenkill21","#520":"Cassiogrimmler","#521":"DominusRay25","#522":"brunoporto14","#523":"LordKagruel","#524":"LucasVdCarvalho","#525":"LucasBonanzi","#526":"Mumassauro","#527":"luanvitozxc","#528":"JRRS96","#529":"Pedreams","#530":"Yuricaldas95","#531":"Henrisathler","#532":"AmadeuFL","#533":"BrunoHunterr","#534":"Marxtomm","#535":"SilveRFanGBanG1","#536":"DracoNery","#537":"SlimShadyDETO","#538":"Bobfilho","#539":"Bernardjoe","#540":"luizzzpereira","#541":"soaresof","#542":"BryanGalo10","#543":"RafaelSSEnzo","#544":"SarinaSchneider","#545":"MestreChariego","#546":"Andresiqueira04","#547":"carloscarvalhoj","#548":"ReiMysticJorel","#549":"AlleMuller","#550":"MadMaxxMaximus","#551":"PokeAXFennix","#552":"PedroAvCon17","#553":"DonovanCarvalho","#554":"JthaSanches","#555":"Abextadoooo","#556":"Aledara3383","#557":"MrNelsao","#558":"GagetaGames","#559":"Binhozika01","#560":"Zenakinhow","#561":"Olyneon","#562":"Slashabreu","#563":"Joaophe","#564":"FeanorEss","#565":"Itaiotiohi","#566":"Israelberbigier","#567":"Filipemelo17","#568":"xPL4Y3R1x","#569":"Fesstus","#570":"1pierre0073","#571":"LoxSP","#572":"Mariomfj","#573":"Alexmelo22","#574":"LucasPSM","#575":"Maumausq","#576":"RRogerioS2","#577":"Fir3mind","#578":"Priiscilas2","#579":"Jvalcn","#580":"Richard4KS","#581":"LNDsTSteinar","#582":"Crystalino9","#583":"JayPhellll","#584":"Collares245","#585":"MassaoGuskuma","#586":"013Mabilabrisa"}