{"#1":"XxRFPOxX","#2":"JWNaldo","#3":"JVitorAmaral","#4":"Rargef","#5":"Copperkid","#6":"GabrielYehovah","#7":"6rajraj9","#8":"Caio06342","#9":"DaniloCalvalhan","#10":"PaulinhoTad","#11":"Hybridonn","#12":"BruceSantos","#13":"IchiroFukuda","#14":"Zarddy","#15":"Hgp2306","#16":"PachoBlues","#17":"RickManzato","#18":"MillerLav","#19":"LihPelinson","#20":"Pedro367428","#21":"Danilo8708","#22":"danielrg98","#23":"FrankWill","#24":"hutral","#25":"CalmaMoreno","#26":"SSchneider33","#27":"Andre10Salles","#28":"Dricolino21","#29":"XJoaoVgmr2006X","#30":"EhhhUsGuri","#31":"VictorHug09","#32":"Danacrisc","#33":"LeunammeGO","#34":"DanielP4l4d1n0","#35":"MestreMendes25","#36":"Yuri220","#37":"FranKDA7","#38":"ShainnerSenpai","#39":"Lokoferas","#40":"PrazerChris","#41":"AureoCerezer","#42":"lpmello84","#43":"JamMustang","#44":"Wenigengel","#45":"beergaaa","#46":"Quindinzinho97","#47":"PachirisuDaDawn","#48":"Washingtonpk1","#49":"JeanCostaJesus","#50":"Allishow10","#51":"Postin","#52":"ThiagoEloyy","#53":"Bruninho69","#54":"wmoliva","#55":"TrnrLucas10","#56":"Augusto11082006","#57":"J34N147","#58":"ReiiiThur","#59":"llRenanJafall","#60":"Firmin0wtwo30","#61":"AbnerOriel","#62":"Mainha03","#63":"Barbosafc","#64":"Lwingzz","#65":"DarknessKyu","#66":"Silvarts","#67":"Leaozinho","#68":"V1v12n","#69":"Kino26LL","#70":"Amancio1401","#71":"Nightmare9113","#72":"Umbuw","#73":"Gabzis","#74":"giantboulder","#75":"OrochiDsM","#76":"Dinagoras","#77":"Ismahell","#78":"ViniConrado97","#79":"MaximeCraft","#80":"jeff05valor","#81":"soul9litch","#82":"Nilimpetuoso","#83":"Wallacesd","#84":"Mustang2795","#85":"leh29","#86":"fernanomaster","#87":"PedroAC07","#88":"PicasoRC","#89":"mferratto","#90":"Jojomura","#91":"Alves75","#92":"lukamrs","#93":"Paulonetaaa09","#94":"Maaelangelii","#95":"Anteriin","#96":"carlosPianta","#97":"JungonJungon","#98":"NaraLago","#99":"sachura77","#100":"Zellgades","#101":"Hatiim","#102":"RafaCarolPrado","#103":"NathanJettar1","#104":"srateta","#105":"GianRedghost","#106":"YuriBrCe","#107":"AWildPinguim","#108":"Coutinho805","#109":"BTowersKA","#110":"RubenCanudo","#111":"Bittenca","#112":"Edersongomes01","#113":"racsphd","#114":"MrXanddy","#115":"thiasccp","#116":"01SgtBrave","#117":"ErickRagnarson","#118":"JoaoLeXavier","#119":"rennangardoni","#120":"wpachecao","#121":"IgorIate","#122":"SirLucasAkio","#123":"KahB57_yt","#124":"MavrousIZN","#125":"NakaMH19","#126":"MaelAngeli","#127":"Kaiorf","#128":"PatrickSRN","#129":"RaltsDoWally","#130":"BeFricke","#131":"Zambleman","#132":"LawrenceLtyear","#133":"RuudG007","#134":"renamolo22364","#135":"CleristonVieira","#136":"xXJohnVitorXx","#137":"Gankakudias","#138":"Matheusbigdaddy","#139":"Felipeborges28","#140":"PatrickyAlbani","#141":"Macciola","#142":"brunohadji","#143":"LTiugansii","#144":"DerekFernanfo","#145":"GustavoYoukai","#146":"xxEdddxx","#147":"Toxicosdiversos","#148":"franciscofrr","#149":"Anderlanm","#150":"Yoshiedson","#151":"marcuspopo","#152":"Grandjyn","#153":"MariaCabralz","#154":"Mahack6","#155":"LOPES1512","#156":"Killjoypg","#157":"MasterGuhhh1","#158":"Fernandim88","#159":"nathassiaaa","#160":"ZzAndromedazZ","#161":"MetallicaJunior","#162":"Dkcerberus","#163":"Liberalino","#164":"Bruno2nunes","#165":"CAIERAGOD","#166":"dehdis","#167":"TheVPSF","#168":"CledilsonRock93","#169":"Wallycastro","#170":"Beninho2015","#171":"Hugo00m","#172":"Kobinha23","#173":"ImperadordoMarX","#174":"Abmdragond","#175":"bbast0s","#176":"LincaoXD","#177":"caiioLim4","#178":"Gbbernardoo","#179":"GuiDSGomes","#180":"AndreyAvilla","#181":"GeneralLeonardo","#182":"Sonozzy","#183":"Xexeu007","#184":"Anders0nc0sta","#185":"LuisRJ21","#186":"XGUIKEN","#187":"MariaAntoniaRJ","#188":"Mateusvalerio","#189":"Lliw","#190":"HyPiN0S","#191":"JoaoNeves200","#192":"JosihelCBF","#193":"EsdrasLBA","#194":"Corinthians10","#195":"ValarM0rghuls","#196":"Batto001","#197":"GusNovalis","#198":"HHideo21","#199":"FelipedeCastroR","#200":"MasterOfReality","#201":"Pronemarmote","#202":"Guleal147","#203":"withebaityou","#204":"DANMOS7","#205":"EDIPAOQSHINY","#206":"ANDERSONSFBR","#207":"TeobaldoE","#208":"TheGugaa","#209":"BobMendesBR","#210":"Argila","#211":"PizzaDelivery","#212":"FiEmery","#213":"GLL182","#214":"FRANKLINROCK","#215":"KrisAlucard","#216":"GabrielCastr007","#217":"Caiozuzuz","#218":"DanAvec","#219":"HullkR","#220":"K1ngNier","#221":"FofaoRadical","#222":"lilomunhos","#223":"Coroachato","#224":"Maumausq","#225":"bibivenditti","#226":"Myla582","#227":"caioLim4","#228":"ReiMysticJorel","#229":"LeeoBadboy","#230":"HaardFV","#231":"SUNtrosko","#232":"rxLinkCarvalho","#233":"Tautenhain1","#234":"ArielRuther","#235":"Lausenger","#236":"S0LUC0","#237":"Lagranha","#238":"gostzin","#239":"AlphaLeonN","#240":"DouglasAzeredo","#241":"mileregou","#242":"JohnSimoes99","#243":"Seilah77EGE","#244":"xLudvig","#245":"Ricellylb","#246":"Extreme78","#247":"Lipevolpi12","#248":"EvansRitzel","#249":"Murdock3215","#250":"TeoS556","#251":"AnderBaracho","#252":"JuniorRubempre","#253":"BrunoSouza72","#254":"Ledzep07","#255":"LoboKetchum81","#256":"Soulindo95","#257":"BreakBruno","#258":"fantasminha","#259":"montonevlogs","#260":"CarlosWessling","#261":"FTSTCNoName","#262":"Lucasneee","#263":"MDeAzevedo","#264":"GabsL08","#265":"RecrutaER","#266":"DushtanoJoey","#267":"seraosleumas","#268":"PocoYo16","#269":"IrvingVegano","#270":"CiAnNeto","#271":"Gerson","#272":"LuannPhillips","#273":"GederEller","#274":"Rapha26R","#275":"Rique627","#276":"Uapuem","#277":"FFernan10","#278":"JayaOkada","#279":"JaoPretoo","#280":"Phvintetres","#281":"01PHP","#282":"LokoDosArames","#283":"Ian93juca","#284":"Raphaaaaaael","#285":"ATomy","#286":"giftflyZ","#287":"RphRodrigues","#288":"FSCASTANON","#289":"l4pdenis","#290":"Zenakinhow","#291":"Ryan1229super","#292":"xxVOLKNERxx","#293":"Lrmarcaljr","#294":"DanielAugusto","#295":"Jhunio86","#296":"Logan94","#297":"GuiliMash","#298":"Acostenha","#299":"BrunoPeron82","#300":"Wellsheldon","#301":"ScientistMike08","#302":"Sofiadamae","#303":"alex23111986","#304":"JoeWillian","#305":"ejuliocrl7","#306":"LeoRezende88","#307":"Alex90oliveira","#308":"Legend2BR","#309":"Anaaluiz4","#310":"88Nossila","#311":"JoaquimBrondani","#312":"XxDartaNxX","#313":"marcelofasal","#314":"GscRed","#315":"DominusRay25","#316":"Didi1977","#317":"AlCunha33","#318":"Beiruteyes","#319":"Barros","#320":"deivisaldren","#321":"LucasBonanzi","#322":"Mumassauro","#323":"LordV610r","#324":"Yuricaldas95","#325":"AmadeuFL","#326":"TaisFigueroa","#327":"BrunoHunterr","#328":"Marxtomm","#329":"DracoNery","#330":"Bernardjoe","#331":"RafaelSSEnzo","#332":"soaresof","#333":"SarinaSchneider","#334":"MadMaxxMaximus","#335":"OmeleteDeTogepi","#336":"TinhoStyle","#337":"Abextadoooo","#338":"ZeDoSambaxxx","#339":"KlausMyth","#340":"Binhozika01","#341":"Andresiqueira04","#342":"MrNelsao","#343":"Kau198","#344":"Slashabreu","#345":"TheGaviao","#346":"FeanorEss","#347":"Israelberbigier","#348":"Mariomfj","#349":"1XTREINERSP20","#350":"Jhonnedenis44","#351":"Olyneon","#352":"Evaldofilhoo","#353":"Priiscilas2","#354":"Rafa1cs","#355":"Brunaaaauum","#356":"Richard4KS","#357":"Collares245","#358":"Tigman1986","#359":"MassaoGuskuma","#360":"ChuckSR","#361":"013Mabilabrisa","#362":"DegoTheHammer","#363":"GustavoFdeSouza","#364":"LucasVdCarvalho","#365":"CarlosCostta","#366":"baresta","#367":"MiraiToranksu","#368":"BrancoFonseca","#369":"Anderson2374","#370":"DanielGaldi","#371":"ParaibaDragon","#372":"KingPissolato","#373":"Marciano0017","#374":"RodrigoSathler","#375":"ThallesFSantos","#376":"AnailtOnSantOs","#377":"18SHARP","#378":"IceToy","#379":"115rj","#380":"TkoAFF","#381":"Henrisathler","#382":"Ooooodaiiii"}