{"#1":"JWNaldo","#2":"Copperkid","#3":"Dricolino21","#4":"ShainnerSenpai","#5":"GabrielYehovah","#6":"JVitorAmaral","#7":"xJoaoVictor2006","#8":"DanielP4l4d1n0","#9":"XxRFPOxX","#10":"Quindinzinho97","#11":"Danacrisc","#12":"LihPelinson","#13":"Hgp2306","#14":"lpmello84","#15":"Yuri220","#16":"TrnrLucas10","#17":"DaniloCalvalhan","#18":"Zarddy","#19":"hutral","#20":"PachoBlues","#21":"6rajraj9","#22":"BTowersKA","#23":"CalmaMoreno","#24":"Maaelangelii","#25":"AureoCerezer","#26":"JamMustang","#27":"Andre10Salles","#28":"PachirisuDaDawn","#29":"Caio06342","#30":"PaulinhoTad","#31":"Rargef","#32":"SSchneider33","#33":"Postin","#34":"MillerLav","#35":"LeunammeGO","#36":"BeFricke","#37":"ThiagoEloyy","#38":"GianRedghost","#39":"IchiroFukuda","#40":"FrankWill","#41":"Pedro367428","#42":"Hybridonn","#43":"Nightmare9113","#44":"Barbosafc","#45":"BruceSantos","#46":"ViniConrado97","#47":"nathassiaaa","#48":"AbnerOriel","#49":"RickManzato","#50":"wmoliva","#51":"JungonJungon","#52":"Allishow10","#53":"Leaozinho","#54":"Danilo8708","#55":"Anderlanm","#56":"VictorHug09","#57":"fernanomaster","#58":"sachura77","#59":"Lokoferas","#60":"NaraLago","#61":"danielrg98","#62":"IgorIate","#63":"Washingtonpk1","#64":"RaltsDoWally","#65":"Jojomura","#66":"MestreMendes25","#67":"rennangardoni","#68":"Firmin0wtwo30","#69":"Wenigengel","#70":"EhhhUsGuri","#71":"beergaaa","#72":"Zellgades","#73":"giantboulder","#74":"PrazerChris","#75":"Leticiaa29","#76":"Augusto11082006","#77":"Mustang2795","#78":"marcuspopo","#79":"Nilimpetuoso","#80":"JeanCostaJesus","#81":"MavrousIZN","#82":"V1v12n","#83":"jeff05valor","#84":"llRenanJafall","#85":"FranKDA7","#86":"Kino26LL","#87":"JosihelCBF","#88":"wpachecao","#89":"PatrickSRN","#90":"MaximeCraft","#91":"Bruninho69","#92":"DarknessKyu","#93":"Silvarts","#94":"Hamuzeira","#95":"LincaoXD","#96":"MaelAngeli","#97":"Anteriin","#98":"mferratto","#99":"Anders0nc0sta","#100":"Alves75","#101":"J34N147","#102":"soul9litch","#103":"Paulonetaaa09","#104":"LOPES1512","#105":"01SgtBrave","#106":"NakaMH19","#107":"Toxicosdiversos","#108":"LawrenceLtyear","#109":"MariaCabralz","#110":"Grandjyn","#111":"ReiiiThur","#112":"Lwingzz","#113":"Umbuw","#114":"Edersongomes01","#115":"franciscofrr","#116":"GLL182","#117":"Dinagoras","#118":"BobMendesBR","#119":"Felipeborges28","#120":"Marciano0017","#121":"thiasccp","#122":"srateta","#123":"FelipeCaRamalho","#124":"Ismahell","#125":"RafaCarolPrado","#126":"Wallacesd","#127":"K1ngNier","#128":"Gabzis","#129":"Amancio1401","#130":"Thiagolima04","#131":"PedroAC07","#132":"OrochiDsM","#133":"GustavoYoukai","#134":"Ledzep07","#135":"Killjoypg","#136":"carlosPianta","#137":"YuriUsedFly","#138":"FiEmery","#139":"HullkR","#140":"Hugo00m","#141":"racsphd","#142":"Mainha03","#143":"lukamrs","#144":"Hatiim","#145":"brunohadji","#146":"bibivenditti","#147":"NathanJettar1","#148":"PicasoRC","#149":"Lausenger","#150":"Kobinha23","#151":"ThenWhyNot","#152":"Coutinho805","#153":"LetsGoGyarados","#154":"LeeoBadboy","#155":"LTiugansii","#156":"RubenCanudo","#157":"Bittenca","#158":"XGUIKEN","#159":"Liberalino","#160":"MrXanddy","#161":"MAJ3STIC99","#162":"robertsouzam","#163":"ErickRagnarson","#164":"TinhoStyle","#165":"JoaoLeXavier","#166":"Kaiorf","#167":"rxLinkCarvalho","#168":"Caiozuzuz","#169":"IrvingVegano","#170":"FFernan10","#171":"Barros","#172":"Faduzim","#173":"Myla582","#174":"KahB57_yt","#175":"GuiliMash","#176":"Abmdragond","#177":"LuisRJ21","#178":"AWildPinguim","#179":"CiAnNeto","#180":"LucLos","#181":"Zambleman","#182":"seraosleumas","#183":"SirLucasAkio","#184":"GusNovalis","#185":"Ian93juca","#186":"RuudG007","#187":"renamolo22364","#188":"CleristonVieira","#189":"xXJohnVitorXx","#190":"Gankakudias","#191":"Aquor002","#192":"Batto001","#193":"ProfessorWilmer","#194":"PatrickyAlbani","#195":"Xexeu007","#196":"Mateusvalerio","#197":"MetallicaJunior","#198":"Brunaaaauum","#199":"DerekFernanfo","#200":"Matheusbigdaddy","#201":"xxEdddxx","#202":"EDIPAOQSHINY","#203":"ZyroBerkXL","#204":"Sirlenekiba","#205":"Yoshiedson","#206":"l4pdenis","#207":"Hudyps93","#208":"PitBandicoot","#209":"Mahack6","#210":"JoaquimBrondani","#211":"Beninho2015","#212":"dehdis","#213":"ImperadordoMarX","#214":"ECPelike","#215":"Wellsheldon","#216":"AlphaLeonN","#217":"Bruno2nunes","#218":"CAIERAGOD","#219":"Gbbernardoo","#220":"FofaoRadical","#221":"Fernandim88","#222":"Willraphas","#223":"Raphaaaaaael","#224":"AndreyXXT","#225":"TheVPSF","#226":"DouglasAzeredo","#227":"CledilsonRock93","#228":"Wallycastro","#229":"WallBrPower","#230":"Lucascaico12","#231":"KlausMyth","#232":"bbast0s","#233":"GuiDSGomes","#234":"RafaXu22","#235":"Seilah77EGE","#236":"AndreyAvilla","#237":"GeneralLeonardo","#238":"HyPiN0S","#239":"caiioLim4","#240":"EsdrasLBA","#241":"Welce10","#242":"erikacostalima","#243":"MariaAntoniaRJ","#244":"JoaoNeves200","#245":"TheGugaa","#246":"ZzAndromedazZ","#247":"ZeDoSambaxxx","#248":"Argila","#249":"JayaOkada","#250":"Corinthians10","#251":"ValarM0rghuls","#252":"1RhuanFelippe1","#253":"Renato0Ze","#254":"andersonbobby","#255":"MasterOfReality","#256":"Sonozzy","#257":"LMJBRAZIL1","#258":"Guleal147","#259":"withebaityou","#260":"AlCunha33","#261":"DANMOS7","#262":"Ricellylb","#263":"DihNalin","#264":"ANDERSONSFBR","#265":"JoeWillian","#266":"ProfNobrega","#267":"PizzaDelivery","#268":"R3N3R4715D","#269":"FRANKLINROCK","#270":"KrisAlucard","#271":"GabrielCastr007","#272":"TheGaviao","#273":"DanAvec","#274":"Macciola","#275":"RecrutaER","#276":"TeoS556","#277":"TaikiriSaruman","#278":"lilomunhos","#279":"AnderBaracho","#280":"Coroachato","#281":"TheBestGarcia","#282":"caioLim4","#283":"Jecatherina","#284":"HaardFV","#285":"Paulovgv007","#286":"Tautenhain1","#287":"ArielRuther","#288":"S0LUC0","#289":"Lagranha","#290":"gostzin","#291":"LimaArleson","#292":"JohnSimoes99","#293":"montonevlogs","#294":"mileregou","#295":"RphRodrigues","#296":"Lliw","#297":"Extreme78","#298":"Lipevolpi12","#299":"TaisFigueroa","#300":"EvansRitzel","#301":"Murdock3215","#302":"BlueGraad","#303":"brunofo18","#304":"JuniorRubempre","#305":"LoboKetchum81","#306":"Beiruteyes","#307":"MDeAzevedo","#308":"Logan94","#309":"Soulindo95","#310":"Bragabis","#311":"fantasminha","#312":"BreakBruno","#313":"FTSTCNoName","#314":"Lucasneee","#315":"MasterGuhhh1","#316":"CarlosWessling","#317":"Jhonnedenis44","#318":"GabsL08","#319":"ChuckSR","#320":"DushtanoJoey","#321":"Lipe bolzan","#322":"PocoYo16","#323":"baresta","#324":"giftflyZ","#325":"Gerson","#326":"LuannPhillips","#327":"Rapha26R","#328":"MarcosCaseira","#329":"Rique627","#330":"GederEller","#331":"Uapuem","#332":"Rafa1cs","#333":"JaoPretoo","#334":"Jhunio86","#335":"01PHP","#336":"115rj","#337":"GabrielNolte","#338":"Phvintetres","#339":"ATomy","#340":"EvertonCMachado","#341":"RNReis","#342":"XYSllagrymaYX","#343":"Alex90oliveira","#344":"FSCASTANON","#345":"Zenakinhow","#346":"TeobaldoE","#347":"aaaaaaaaaaQPOHA","#348":"LokoDosArames","#349":"xxVOLKNERxx","#350":"DanielAugusto","#351":"Lrmarcaljr","#352":"LordV610r","#353":"Emiliana75","#354":"fantasminha688","#355":"Ryan1229super","#356":"Ffaabricioo","#357":"Acostenha","#358":"GisaDylon","#359":"BrunoPeron82","#360":"Maguugam","#361":"CacahLacerda","#362":"SUNtrosko","#363":"alex23111986","#364":"ScientistMike08","#365":"ejuliocrl7","#366":"BrancoFonseca","#367":"LeoRezende88","#368":"Reevoltz00","#369":"Legend2BR","#370":"Bl4cklivematter","#371":"Anaaluiz4","#372":"MrSchaeffer","#373":"88Nossila","#374":"XxDartaNxX","#375":"WellKING1","#376":"TamagXolitario","#377":"VantuildesTUTU","#378":"KomachiHero","#379":"jbarbosa","#380":"marcelofasal","#381":"rogerblake","#382":"GscRed","#383":"Ghunnter","#384":"Cassiogrimmler","#385":"DominusRay25","#386":"Didi1977","#387":"LordKagruel","#388":"Evaldofilhoo","#389":"deivisaldren","#390":"jvcpBR","#391":"LucasBonanzi","#392":"Mumassauro","#393":"Felipesp3456","#394":"luanvitozxc","#395":"Pedreams","#396":"Yuricaldas95","#397":"Henrisathler","#398":"AmadeuFL","#399":"BrunoHunterr","#400":"Pudim8D","#401":"DracoNery","#402":"Bobfilho","#403":"Bernardjoe","#404":"soaresof","#405":"RafaelSSEnzo","#406":"SarinaSchneider","#407":"carloscarvalhoj","#408":"MadMaxxMaximus","#409":"OmeleteDeTogepi","#410":"PokeAXFennix","#411":"DonovanCarvalho","#412":"Abextadoooo","#413":"EuDaniloGabriel","#414":"Andresiqueira04","#415":"MrNelsao","#416":"ReiMysticJorel","#417":"Binhozika01","#418":"PedroAvCon17","#419":"Olyneon","#420":"JhonOliveira10","#421":"Pronemarmote","#422":"ThallesFSantos","#423":"Slashabreu","#424":"FeanorEss","#425":"Israelberbigier","#426":"kdminhaconta","#427":"Mariomfj","#428":"Maumausq","#429":"DudumonXY","#430":"Fir3mind","#431":"Priiscilas2","#432":"DegoTheHammer","#433":"Richard4KS","#434":"JayPhellll","#435":"Collares245","#436":"Tigman1986","#437":"MassaoGuskuma","#438":"Dannyyllo","#439":"013Mabilabrisa","#440":"Felipemelokkk","#441":"Sofiadamae","#442":"GustavoFdeSouza","#443":"LucasVdCarvalho","#444":"Hermesalves","#445":"CarlosCostta","#446":"MiraiToranksu","#447":"yDuDuLe1","#448":"Anderson2374","#449":"KingPissolato","#450":"XavecoJoao","#451":"RodrigoSathler","#452":"CarlosPaiva40","#453":"AnailtOnSantOs","#454":"Lukinhasdz77","#455":"1XTREINERSP20","#456":"18SHARP","#457":"DanielGaldi","#458":"DenizMphee357"}