{"#1":"PachirisuDaDawn","#2":"LNDsBernardo","#3":"xJoaoVictor2006","#4":"BruceSantos","#5":"LordAdanThierry","#6":"BMsGageta","#7":"PrazerChris","#8":"LNDsAureo","#9":"Marcito88","#10":"PaiDoLuke7","#11":"BMsMael","#12":"Yuri220","#13":"anonimitozxc","#14":"BMPlayerSincero","#15":"ImperadordoMarX","#16":"LucLos","#17":"WELLDGP","#18":"BMsLeoBgi018","#19":"Andre10Salles","#20":"ErivaldoSkull","#21":"V1v12n","#22":"BwzGreenkillXXl","#23":"TheLastJed1","#24":"CruzDanjo88","#25":"PaulinhoTad","#26":"DheVooox","#27":"MrJuanAstete","#28":"kayobr78","#29":"Coroachato","#30":"Zarddy","#31":"REN4N015","#32":"RphRodrigues","#33":"SullivanCarlos","#34":"gesouza","#35":"Vitorl3o","#36":"HarrisLee88","#37":"Kau198","#38":"BWzAmbersinoh","#39":"thiasccp","#40":"Lokoferas","#41":"xDaniloJmm","#42":"XxPGSxXEdu29NBR","#43":"AbnerOriel","#44":"CarlosWessling","#45":"Eduardohsg0311","#46":"CauTx","#47":"Awasok","#48":"Leticiaa29","#49":"Digones151","#50":"Moriartxy","#51":"AnuarTuma","#52":"PatrickyAlbani","#53":"CalmaMoreno","#54":"Magruus","#55":"Laioshow","#56":"XxLordeAnjoxX","#57":"LCostinha19","#58":"EduardoBorba86","#59":"MestreChariego","#60":"1pierre0073","#61":"marceltetzel","#62":"Hari2277","#63":"Fabas","#64":"JamMustang","#65":"TarcisioEnzo","#66":"ArcanoSlz","#67":"BabiSyl","#68":"Aprendizmestre","#69":"Dragalger","#70":"Tabuada28","#71":"WagnerLendario","#72":"ScientistMike08","#73":"Mainha03","#74":"MyGIShainner","#75":"KcyuLeite43","#76":"RicardoVelho","#77":"RenataDz","#78":"YGabriel1991","#79":"Juhsmuniz","#80":"LliwLopes","#81":"KaidWP","#82":"SillasTY","#83":"Jhunio86","#84":"TheOldDrico","#85":"PatrickSRN","#86":"VLuDwiG1","#87":"Kaiorf","#88":"TaisFigueroa","#89":"GeneralLeonardo","#90":"erikacostalima","#91":"GanDokZ","#92":"SeuBirino","#93":"giantboulder","#94":"Gbbernardoo","#95":"Nelsu","#96":"RubenCanudo","#97":"xXJohnVitorXx","#98":"MyGRaphaelSB","#99":"OmeleteDeTogepi","#100":"MasterWhoiss","#101":"Zenakinhow","#102":"BrunolCoviD","#103":"TFFJardim23","#104":"Sesski223","#105":"DVsDANMOS7","#106":"SuperSaiyaJean","#107":"PedroAC07","#108":"Bajogun","#109":"RainerLeal","#110":"Man3394","#111":"xXRoseNatalieXx","#112":"RaffuwMartins"}