{"#1":"DaniloCalvalhan","#2":"R0ssinh0","#3":"soul9litch","#4":"JWNaldo","#5":"MillerLav","#6":"Dricolino21","#7":"Hybridonn","#8":"PrazerChris","#9":"VictorHug09","#10":"Ismahell","#11":"Pedro367428","#12":"Caio06342","#13":"PachoBlues","#14":"Maaelangelii","#15":"Copperkid","#16":"XxRFPOxX","#17":"Danilo8708","#18":"danielrg98","#19":"AureoCerezer","#20":"Hgp2306","#21":"MaximeCraft","#22":"Kino26LL","#23":"GabrielYehovah","#24":"Hatiim","#25":"Fernandim88","#26":"NathanJettar1","#27":"Rargef","#28":"PachirisuDaDawn","#29":"BruceSantos","#30":"Mainha03","#31":"MestreMendes25","#32":"PaulinhoTad","#33":"JamMustang","#34":"MrXanddy","#35":"Danacrisc","#36":"ErickRagnarson","#37":"CalmaMoreno","#38":"DanielP4l4d1n0","#39":"Washingtonpk1","#40":"Andre10Salles","#41":"Gabzis","#42":"Bruninho69","#43":"fernanomaster","#44":"Yuri220","#45":"wmoliva","#46":"KahB57_yt","#47":"Nilimpetuoso","#48":"JVitorAmaral","#49":"FrankWill","#50":"PatrickSRN","#51":"AbnerOriel","#52":"ReiiiThur","#53":"Lwingzz","#54":"LihPelinson","#55":"rennangardoni","#56":"DarknessKyu","#57":"RuudG007","#58":"YuriBrCe","#59":"FranKDA7","#60":"Postin","#61":"RickManzato","#62":"PatrickyAlbani","#63":"SSchneider33","#64":"RafaCarolPrado","#65":"Zarddy","#66":"sachura77","#67":"Toxicosdiversos","#68":"ThiagoEloyy","#69":"Marcosvsm82","#70":"Leaozinho","#71":"ZzAndromedazZ","#72":"MaelAngeli","#73":"Wenigengel","#74":"JeanCostaJesus","#75":"DerekFernanfo","#76":"wpachecao","#77":"Quindinzinho97","#78":"Coutinho805","#79":"Wallacesd","#80":"lukamrs","#81":"lpmello84","#82":"6rajraj9","#83":"Nightmare9113","#84":"Silvarts","#85":"Liberalino","#86":"J34N147","#87":"TrnrLucas10","#88":"giantboulder","#89":"thiasccp","#90":"TheVPSF","#91":"MavrousIZN","#92":"NaraLago","#93":"IchiroFukuda","#94":"Umbuw","#95":"hutral","#96":"EhhhUsGuri","#97":"Alves75","#98":"ShainnerSenpai","#99":"caiioLim4","#100":"AndreyAvilla","#101":"GeneralLeonardo","#102":"V1v12n","#103":"PizzaDelivery","#104":"HyPiN0S","#105":"GustavoYoukai","#106":"PedroAC07","#107":"01SgtBrave","#108":"EsdrasLBA","#109":"Augusto11082006","#110":"IgorIate","#111":"Corinthians10","#112":"ValarM0rghuls","#113":"Batto001","#114":"Yoshiedson","#115":"Anderlanm","#116":"MasterOfReality","#117":"Guleal147","#118":"Amancio1401","#119":"withebaityou","#120":"BTowersKA","#121":"BobMendesBR","#122":"DANMOS7","#123":"LeunammeGO","#124":"ANDERSONSFBR","#125":"Anteriin","#126":"FiEmery","#127":"KrisAlucard","#128":"HullkR","#129":"Toxao18","#130":"Matheusbigdaddy","#131":"OmeleteDeTogepi","#132":"franciscofrr","#133":"nathassiaaa","#134":"ViniConrado97","#135":"Ian93juca","#136":"LeeoBadboy","#137":"Beninho2015","#138":"Barbosafc","#139":"HaardFV","#140":"carlosPianta","#141":"MDeAzevedo","#142":"RubenCanudo","#143":"racsphd","#144":"Jojomura","#145":"S0LUC0","#146":"caioLim4","#147":"gostzin","#148":"BeFricke","#149":"MrNelsao","#150":"Anders0nc0sta","#151":"ChuckSR","#152":"Mahack6","#153":"JohnSimoes99","#154":"Firmin0wtwo30","#155":"afonsocmmelo","#156":"Extreme78","#157":"EvansRitzel","#158":"Murdock3215","#159":"XJoaoVgmr2006X","#160":"Hugo00m","#161":"Dinagoras","#162":"AnderBaracho","#163":"JuniorRubempre","#164":"seraosleumas","#165":"MasterGuhhh1","#166":"xXJohnVitorXx","#167":"AWildPinguim","#168":"LoboKetchum81","#169":"Zenakinhow","#170":"Lucasneee","#171":"Kaiorf","#172":"JungonJungon","#173":"ThallesFSantos","#174":"marcuspopo","#175":"DracoNery","#176":"Anaaluiz4","#177":"DushtanoJoey","#178":"Allishow10","#179":"Gerson","#180":"CiAnNeto","#181":"mileregou","#182":"Rapha26R","#183":"Rique627","#184":"JayaOkada","#185":"JaoPretoo","#186":"Mateusvalerio","#187":"GuiDSGomes","#188":"Phvintetres","#189":"FelipedeCastroR","#190":"alex23111986","#191":"giftflyZ","#192":"RphRodrigues","#193":"Zambleman","#194":"FFernan10","#195":"CarlosWessling","#196":"FSCASTANON","#197":"LincaoXD","#198":"MariaCabralz","#199":"CleristonVieira","#200":"LoxSP","#201":"CledilsonRock93","#202":"Zellgades","#203":"LuisRJ21","#204":"xLudvig","#205":"TeobaldoE","#206":"Wellsheldon","#207":"Didi1977","#208":"ArielRuther","#209":"Paulonetaaa09","#210":"Gbbernardoo","#211":"Lausenger","#212":"leh29","#213":"XxDartaNxX","#214":"GuiliMash","#215":"ReiMysticJorel","#216":"DominusRay25","#217":"beergaaa","#218":"DanielGaldi","#219":"AlCunha33","#220":"xxEdddxx","#221":"rxLinkCarvalho","#222":"Bruno2nunes","#223":"LucasBonanzi","#224":"Coroachato","#225":"Yuricaldas95","#226":"Argila","#227":"NakaMH19","#228":"AmadeuFL","#229":"BrunoHunterr","#230":"marcelofasal","#231":"Marxtomm","#232":"Bernardjoe","#233":"Israelberbigier","#234":"soaresof","#235":"SarinaSchneider","#236":"Lrmarcaljr","#237":"FofaoRadical","#238":"Alex90oliveira","#239":"Legend2BR","#240":"Abextadoooo","#241":"lilomunhos","#242":"Andresiqueira04","#243":"Minixexeu","#244":"Dkcerberus","#245":"Willraphas","#246":"Slashabreu","#247":"TheGaviao","#248":"42Marcelo","#249":"GabrielCastr007","#250":"Mariomfj","#251":"Soulindo95","#252":"01PHP","#253":"Olyneon","#254":"xxVOLKNERxx","#255":"bbast0s","#256":"Rafa1cs","#257":"GusNovalis","#258":"Brunaaaauum","#259":"ImperadordoMarX","#260":"Mumassauro","#261":"Myla582","#262":"Jhonnedenis44","#263":"Jhunio86","#264":"BrunoPeron82","#265":"K1ngNier","#266":"GustavoFdeSouza","#267":"LucasVdCarvalho","#268":"TeoS556","#269":"CarlosCostta","#270":"MiraiToranksu","#271":"Anderson2374","#272":"MassaoGuskuma","#273":"Gankakudias","#274":"Marciano0017","#275":"Seilah77EGE","#276":"WallBrPower","#277":"AnailtOnSantOs","#278":"SirLucasAkio","#279":"jeff05valor","#280":"TkoAFF","#281":"Lipevolpi12"}